{
  "_class": "artboard",
  "backgroundColor": {
    "_class": "color",
    "alpha": 1,
    "blue": 1,
    "green": 1,
    "red": 1
  },
  "booleanOperation": -1,
  "clippingMaskMode": 0,
  "do_objectID": "9D00D067-DA62-4076-A913-43865B7EA62A",
  "exportOptions": {
    "_class": "exportOptions",
    "exportFormats": [
      {
        "_class": "exportFormat",
        "absoluteSize": 0,
        "fileFormat": "png",
        "name": "",
        "namingScheme": 0,
        "scale": 1,
        "visibleScaleType": 0
      }
    ],
    "includedLayerIds": [
    ],
    "layerOptions": 0,
    "shouldTrim": false
  },
  "frame": {
    "_class": "rect",
    "constrainProportions": false,
    "height": 100,
    "width": 600,
    "x": 176,
    "y": 2209
  },
  "hasBackgroundColor": false,
  "hasClickThrough": true,
  "hasClippingMask": false,
  "horizontalRulerData": {
    "_class": "rulerData",
    "base": 0,
    "guides": [
    ]
  },
  "includeBackgroundColorInExport": true,
  "includeInCloudUpload": true,
  "isFixedToViewport": false,
  "isFlippedHorizontal": false,
  "isFlippedVertical": false,
  "isFlowHome": false,
  "isLocked": false,
  "isVisible": true,
  "layerListExpandedType": 1,
  "layers": [
    {
      "class": "rectangle",
      "id": "08A58734-9231-4EC1-BC30-70F247BD471C"
    },
    {
      "class": "symbolInstance",
      "id": "40F1F857-2F0D-4F95-A508-23AA125215EB"
    },
    {
      "class": "symbolInstance",
      "id": "BA8721B3-5DAC-4AA7-B0DE-950E714106B1"
    },
    {
      "class": "symbolInstance",
      "id": "6450DC9A-CFFD-4721-8A78-B79987D00D0B"
    },
    {
      "class": "symbolInstance",
      "id": "116E771C-0104-4530-BD86-4B02C8D18FBB"
    },
    {
      "class": "symbolInstance",
      "id": "10EDE539-F9DC-42FD-9BF5-A9FBF83EA3F8"
    },
    {
      "class": "symbolInstance",
      "id": "F6C35962-9CCC-4CB0-8D66-1D36B449CA3E"
    }
  ],
  "name": "20 Question",
  "nameIsFixed": true,
  "presetDictionary": {
    "allowResizedMatching": 0,
    "height": 100,
    "name": "Logo UserReport",
    "offersLandscapeVariant": 0,
    "width": 400
  },
  "resizesContent": false,
  "resizingConstraint": 63,
  "resizingType": 0,
  "rotation": 0,
  "shouldBreakMaskChain": true,
  "style": {
    "_class": "style",
    "endMarkerType": 0,
    "miterLimit": 10,
    "startMarkerType": 0,
    "windingRule": 1
  },
  "userInfo": {
    "com.animaapp.stc-sketch-plugin": {
      "kModelPropertiesKey": {
      }
    }
  },
  "verticalRulerData": {
    "_class": "rulerData",
    "base": 0,
    "guides": [
    ]
  }
}