{
  "_class": "group",
  "booleanOperation": -1,
  "clippingMaskMode": 0,
  "do_objectID": "CFE5D72D-6021-498B-8DF8-27989A210490",
  "exportOptions": {
    "_class": "exportOptions",
    "exportFormats": [
    ],
    "includedLayerIds": [
    ],
    "layerOptions": 0,
    "shouldTrim": false
  },
  "frame": {
    "_class": "rect",
    "constrainProportions": false,
    "height": 320,
    "width": 1440,
    "x": 0,
    "y": 56
  },
  "hasClickThrough": false,
  "hasClippingMask": false,
  "isFixedToViewport": false,
  "isFlippedHorizontal": false,
  "isFlippedVertical": false,
  "isLocked": false,
  "isVisible": true,
  "layerListExpandedType": 0,
  "layers": [
    {
      "class": "symbolInstance",
      "id": "325A7896-BD24-4CB4-BEB9-E51922FE52E4"
    },
    {
      "class": "symbolInstance",
      "id": "F12738BF-9BDD-4FCC-8419-45AA13E537D1"
    },
    {
      "class": "symbolInstance",
      "id": "BB91A4E6-ACD7-452E-9F9E-E1C5EF038010"
    }
  ],
  "name": "Stacked Group",
  "nameIsFixed": false,
  "resizingConstraint": 63,
  "resizingType": 0,
  "rotation": 0,
  "shouldBreakMaskChain": false,
  "style": {
    "_class": "style",
    "endMarkerType": 0,
    "miterLimit": 10,
    "startMarkerType": 0,
    "windingRule": 1
  },
  "userInfo": {
    "com.animaapp.stc-sketch-plugin": {
      "kModelPropertiesKey": {
        "align": 0,
        "isCollapsing": 1,
        "spacing": 0,
        "stackType": 1
      }
    }
  }
}