{
  "_class": "artboard",
  "backgroundColor": {
    "_class": "color",
    "alpha": 1,
    "blue": 1,
    "do_objectID": "92D414B7-CEF0-4C86-8C83-49C1CE375D3F",
    "green": 1,
    "red": 1
  },
  "booleanOperation": -1,
  "clippingMaskMode": 0,
  "do_objectID": "27C2A88C-49BD-436D-8135-36411D4262D4",
  "exportOptions": {
    "_class": "exportOptions",
    "do_objectID": "0781E1A1-0B4A-4551-88E6-1F4D3AF9EB6B",
    "exportFormats": [
      {
        "_class": "exportFormat",
        "absoluteSize": 0,
        "fileFormat": "png",
        "name": "",
        "namingScheme": 0,
        "scale": 1,
        "visibleScaleType": 0
      }
    ],
    "includedLayerIds": [
    ],
    "layerOptions": 0,
    "shouldTrim": false
  },
  "frame": {
    "_class": "rect",
    "constrainProportions": false,
    "do_objectID": "C9B1508C-F6D9-49AB-904C-992741389760",
    "height": 1024,
    "width": 360,
    "x": 500,
    "y": -354
  },
  "hasBackgroundColor": true,
  "hasClickThrough": true,
  "hasClippingMask": false,
  "horizontalRulerData": {
    "_class": "rulerData",
    "base": 0,
    "do_objectID": "569F182D-AC8A-44C3-9E28-83D8E139BB7A",
    "guides": [
    ]
  },
  "includeBackgroundColorInExport": true,
  "includeInCloudUpload": true,
  "isFixedToViewport": false,
  "isFlippedHorizontal": false,
  "isFlippedVertical": false,
  "isFlowHome": false,
  "isLocked": false,
  "isVisible": true,
  "layerListExpandedType": 0,
  "layers": [
    {
      "class": "group",
      "id": "5B8A1829-A772-43B9-97A7-ACADFDCA803C"
    }
  ],
  "name": "home/forms/add",
  "nameIsFixed": true,
  "presetDictionary": {
    "allowResizedMatching": 0,
    "height": 1024,
    "name": "Desktop",
    "offersLandscapeVariant": 0,
    "width": 1024
  },
  "resizesContent": false,
  "resizingConstraint": 63,
  "resizingType": 0,
  "rotation": 0,
  "shouldBreakMaskChain": true,
  "style": {
    "_class": "style",
    "do_objectID": "2EA7F301-B705-4FD8-8321-D88E53BA514B",
    "endMarkerType": 0,
    "miterLimit": 10,
    "startMarkerType": 0,
    "windingRule": 1
  },
  "userInfo": {
    "com.animaapp.stc-sketch-plugin": {
      "kModelPropertiesKey": {
        "nestedSymbolsCacheKey": "K0o4wNm6wz+3SOitC6+HPCUjqVIFQQWpty6Ty864sJQ="
      }
    }
  },
  "verticalRulerData": {
    "_class": "rulerData",
    "base": 0,
    "do_objectID": "E48828DB-408D-49C9-BE2D-CE8A4935D283",
    "guides": [
    ]
  }
}