{
  "_class": "group",
  "booleanOperation": -1,
  "do_objectID": "3DA8CF85-BE41-45F2-8131-7C4692F1660A",
  "exportOptions": {
    "_class": "exportOptions",
    "exportFormats": [
    ],
    "includedLayerIds": [
    ],
    "layerOptions": 0,
    "shouldTrim": false
  },
  "frame": {
    "_class": "rect",
    "constrainProportions": false,
    "height": 72,
    "width": 87,
    "x": 0,
    "y": 0
  },
  "hasClickThrough": false,
  "isFixedToViewport": false,
  "isFlippedHorizontal": false,
  "isFlippedVertical": false,
  "isLocked": false,
  "isVisible": true,
  "layerListExpandedType": 0,
  "layers": [
    {
      "class": "symbolInstance",
      "id": "E0A61B94-3D76-4BCE-8942-83DB74E0183B"
    },
    {
      "class": "symbolInstance",
      "id": "8F64ECB6-85B8-4FB3-850E-7F3410FAADCF"
    },
    {
      "class": "symbolInstance",
      "id": "6175F4FC-82A0-41EB-867C-B6BC48C52AAB"
    }
  ],
  "name": "Stacked Group",
  "nameIsFixed": false,
  "resizingConstraint": 63,
  "resizingType": 0,
  "rotation": 0,
  "shouldBreakMaskChain": false,
  "style": {
    "_class": "style",
    "endMarkerType": 0,
    "miterLimit": 10,
    "startMarkerType": 0,
    "windingRule": 1
  },
  "userInfo": {
    "com.animaapp.stc-sketch-plugin": {
      "kModelPropertiesKey": {
        "align": 2,
        "isCollapsing": 1,
        "spacing": 0,
        "stackType": 0
      },
      "kViewTypeKey": "ADModelStackView"
    }
  }
}