{
  "_class": "artboard",
  "backgroundColor": {
    "_class": "color",
    "alpha": 1,
    "blue": 1,
    "green": 1,
    "red": 1
  },
  "booleanOperation": -1,
  "clippingMaskMode": 0,
  "do_objectID": "DE47F3B5-6907-440A-A4C5-38C48FCEA462",
  "exportOptions": {
    "_class": "exportOptions",
    "exportFormats": [
      {
        "_class": "exportFormat",
        "absoluteSize": 0,
        "fileFormat": "png",
        "name": "",
        "namingScheme": 0,
        "scale": 1,
        "visibleScaleType": 0
      }
    ],
    "includedLayerIds": [
    ],
    "layerOptions": 0,
    "shouldTrim": false
  },
  "frame": {
    "_class": "rect",
    "constrainProportions": false,
    "height": 100,
    "width": 500,
    "x": 276,
    "y": 339
  },
  "hasBackgroundColor": false,
  "hasClickThrough": true,
  "hasClippingMask": false,
  "horizontalRulerData": {
    "_class": "rulerData",
    "base": 0,
    "guides": [
    ]
  },
  "includeBackgroundColorInExport": true,
  "includeInCloudUpload": true,
  "isFixedToViewport": false,
  "isFlippedHorizontal": false,
  "isFlippedVertical": false,
  "isFlowHome": false,
  "isLocked": false,
  "isVisible": true,
  "layerListExpandedType": 1,
  "layers": [
    {
      "class": "rectangle",
      "id": "0AA2BE77-1D9E-4956-A69F-850B38D7ADBA"
    },
    {
      "class": "symbolInstance",
      "id": "E2D1CD99-7CDC-45AC-AAF3-CB2D89CB65C9"
    },
    {
      "class": "symbolInstance",
      "id": "906030FF-793E-4604-9673-A749CC307EA1"
    },
    {
      "class": "symbolInstance",
      "id": "BF33970E-190A-41FB-96A0-8B03AB2050D9"
    },
    {
      "class": "symbolInstance",
      "id": "8483C3B6-F579-4E6E-8E3F-0D330BAA4B71"
    },
    {
      "class": "symbolInstance",
      "id": "152ED3E3-EB28-4CA2-B1C8-A19C2A38CB99"
    }
  ],
  "name": "Question 3",
  "nameIsFixed": true,
  "presetDictionary": {
    "allowResizedMatching": 0,
    "height": 100,
    "name": "Logo UserReport",
    "offersLandscapeVariant": 0,
    "width": 400
  },
  "resizesContent": true,
  "resizingConstraint": 63,
  "resizingType": 0,
  "rotation": 0,
  "shouldBreakMaskChain": true,
  "style": {
    "_class": "style",
    "endMarkerType": 0,
    "miterLimit": 10,
    "startMarkerType": 0,
    "windingRule": 1
  },
  "userInfo": {
    "com.animaapp.stc-sketch-plugin": {
      "kModelPropertiesKey": {
      }
    }
  },
  "verticalRulerData": {
    "_class": "rulerData",
    "base": 0,
    "guides": [
    ]
  }
}